Spectral_Simulation/__init__.py
Spectral_Simulation/joke.py
Spectral_Simulation-0.1.dist-info/METADATA
Spectral_Simulation-0.1.dist-info/WHEEL
Spectral_Simulation-0.1.dist-info/top_level.txt
Spectral_Simulation-0.1.dist-info/RECORD
