Metadata-Version: 2.1
Name: Spectral-Simulation
Version: 0.1
Summary: Spectral_Simulation taking in H and R
Home-page: http://github.com/storborg/funniest
Author: Flying Circus
Author-email: flyingcircus@example.com
License: MIT
Platform: UNKNOWN
